{
  "Info": "남양동 PC토랑",
  "Version": "1.2",
  "MiningID": "always10",
  "IgnoreLogin": 0,
  "WaitForManagerAfterSecond": 30,
  "StartMiningAfterMinute": 3,
  "StartMiningScriptName": "StartMining.ps1",
  "RestartComputerOnClose": 1,
  "RestartComputerAfterHour": 0,
  "SwitchOffMonitor": 1,
  "SwitchOffMonitorOnMinute": 5,
  "UseProfile": 1,
  "ShowWindow": 1,
  "ExceptNvidiaName": [],
  "ExceptPcNumber": [],
  "ScheduleForePatchOnHour": 0,
  "Profiles": [
    {
      "PcNumber": 0,
      "PowerLimit": 78,
      "ThermalLimit": 65,
      "CoreClkBoost": 0,
      "MemClkBoost": 800000,
      "FanMode": 1,
      "FanSpeed": 25
    }
  ]
}
